lvmtan/.coverage
lvmtan/BasdaCluPythonServiceWorker.py
lvmtan/BasdaMoccaBaseCluPythonServiceWorker.py
lvmtan/BasdaMoccaCluPythonServiceWorker.py
lvmtan/BasdaMoccaTrajCluPythonServiceWorker.py
lvmtan/BasdaMoccaWheelCluPythonServiceWorker.py
lvmtan/BasdaMoccaXCluPythonServiceWorker.py
lvmtan/BasdaMoccaXYCluPythonServiceWorker.py
lvmtan/__init__.py
lvmtan/config/alias.cfg
lvmtan/config/lvm/common/PI_M413.12S_datasheet.conf
lvmtan/config/lvm/common/PI_MICOS_datasheet.conf
lvmtan/config/lvm/common/PI_WHEEL_datasheet.conf
lvmtan/config/lvm/common/datasheetServo.conf
lvmtan/config/lvm/common/datasheetStepper.conf
lvmtan/config/lvm/lvm.all-sim.conf
lvmtan/config/lvm/lvm.all-svr.conf
lvmtan/config/lvm/lvm.all.ui
lvmtan/config/lvm/lvm.moe-mpia.conf
lvmtan/config/lvm/lvm.moe-sim.conf
lvmtan/config/lvm/lvm.moe-svr.conf
lvmtan/config/lvm/sci/foc/lvm.sci.foc-dev.conf
lvmtan/config/lvm/sci/foc/lvm.sci.foc-sim.conf
lvmtan/config/lvm/sci/foc/lvm.sci.foc-svc.conf
lvmtan/config/lvm/sci/foc/lvm.sci.foc-svr.conf
lvmtan/config/lvm/sci/km/lvm.sci.km-dev.conf
lvmtan/config/lvm/sci/km/lvm.sci.km-svc.conf
lvmtan/config/lvm/sci/km/lvm.sci.km-svr.conf
lvmtan/config/lvm/sci/lvm.sci-sim.conf
lvmtan/config/lvm/sci/lvm.sci-svr.conf
lvmtan/config/lvm/skye/foc/lvm.skye.foc-dev.conf
lvmtan/config/lvm/skye/foc/lvm.skye.foc-sim.conf
lvmtan/config/lvm/skye/foc/lvm.skye.foc-svc.conf
lvmtan/config/lvm/skye/foc/lvm.skye.foc-svr.conf
lvmtan/config/lvm/skye/km/lvm.skye.km-dev.conf
lvmtan/config/lvm/skye/km/lvm.skye.km-svc.conf
lvmtan/config/lvm/skye/km/lvm.skye.km-svr.conf
lvmtan/config/lvm/skye/lvm.skye-sim.conf
lvmtan/config/lvm/skye/lvm.skye-svr.conf
lvmtan/config/lvm/skyw/foc/lvm.skyw.foc-dev.conf
lvmtan/config/lvm/skyw/foc/lvm.skyw.foc-sim.conf
lvmtan/config/lvm/skyw/foc/lvm.skyw.foc-svc.conf
lvmtan/config/lvm/skyw/foc/lvm.skyw.foc-svr.conf
lvmtan/config/lvm/skyw/km/lvm.skyw.km-dev.conf
lvmtan/config/lvm/skyw/km/lvm.skyw.km-svc.conf
lvmtan/config/lvm/skyw/km/lvm.skyw.km-svr.conf
sdss_lvmtan-0.3.6.dist-info/LICENSE.md
sdss_lvmtan-0.3.6.dist-info/METADATA
sdss_lvmtan-0.3.6.dist-info/WHEEL
sdss_lvmtan-0.3.6.dist-info/entry_points.txt
sdss_lvmtan-0.3.6.dist-info/RECORD
