Metadata-Version: 2.1
Name: sdss-lvmtan
Version: 0.3.6
Summary: Lvm Tan Clu Wrapper
Home-page: https://github.com/sdss/lvmtan
License: BSD-3-Clause
Keywords: astronomy,software
Author: Florian Briegel
Author-email: briegel@mpia.de
Requires-Python: >=3.8,<4
Classifier: Intended Audience :: Science/Research
Classifier: License :: OSI Approved :: BSD License
Classifier: Natural Language :: English
Classifier: Operating System :: OS Independent
Classifier: Programming Language :: Python :: 3
Classifier: Programming Language :: Python :: 3.8
Classifier: Programming Language :: Python :: 3.9
Classifier: Programming Language :: Python :: 3.10
Classifier: Programming Language :: Python :: 3.11
Classifier: Programming Language :: Python :: 3.12
Classifier: Topic :: Documentation :: Sphinx
Classifier: Topic :: Software Development :: Libraries :: Python Modules
Requires-Dist: sdss-clu (>=2.0.0)
Requires-Dist: sdss-cluplus (>=0.0.1)
Requires-Dist: sdss-lvmtipo (>=0.0.36)
Requires-Dist: sdsstools (>=0.4.0)
Project-URL: Documentation, https://sdss-lvmtan.readthedocs.org
Project-URL: Repository, https://github.com/sdss/lvmtan
